{
  "title": "Chronic Inflammation After 40: The Silent Force Behind Your Symptoms",
  "slug": "chronic-inflammation-after-40",
  "seo_title": "Chronic Inflammation After 40: The Silent Driver",
  "meta_description": "Chronic low-grade inflammation after 40 drives fatigue, pain, weight gain, and brain fog. Learn what causes it and evidence-based ways to reduce it.",
  "primary_keyword": "chronic inflammation after 40",
  "tags": "inflammation, inflammaging, curcumin, women over 40, immune health, anti-inflammatory",
  "cluster": "Immunity",
  "product_handle": "liver-tonic",
  "product_image_url": "https://cdn.shopify.com/s/files/1/0869/3704/3264/files/liver-tonic.jpg",
  "word_count_estimate": 2100,
  "status": "ready"
}
