{
  "title": "CoQ10 for Brain Health After 40: What the Research Actually Shows",
  "slug": "coq10-brain-health-after-40",
  "seo_title": "CoQ10 for Brain Health After 40: What Research Shows",
  "meta_description": "CoQ10 levels drop 30-50% by your 40s, and the brain pays the price. Learn what the clinical research shows about CoQ10 and cognitive function after 40.",
  "primary_keyword": "CoQ10 brain health after 40",
  "tags": "CoQ10, brain health, cognitive function, women over 40, mitochondria, energy, brain tonic",
  "author": "Happy Aging Team",
  "excerpt": "CoQ10 is essential for mitochondrial energy production, and the brain uses 20% of the body's total energy supply. Research shows supplementing with liposomal CoQ10 can improve memory, reduce mental fatigue, and protect neurons from age-related oxidative damage.",
  "product_handle": "brain-tonic",
  "cluster": "BrainHealth",
  "image_query": "woman coq10 brain health healthy lifestyle",
  "body_image_queries": [
    "woman outdoor morning walk",
    "healthy colorful food meal",
    "woman relaxed confident indoor"
  ]
}
