{
  "title": "Morning Routine for Women Over 40: Energy, Focus, and Calm in 30 Minutes",
  "slug": "morning-routine-women-over-40-energy-focus",
  "primary_keyword": "morning routine for women over 40",
  "tags": "morning routine, women over 40, energy, focus, brain health, daily habits, CoQ10",
  "excerpt": "A 30-minute morning routine designed for women over 40 that uses hydration, movement, light exposure, and targeted supplements to restore energy, sharpen focus, and bring calm to every day.",
  "seo_title": "Morning Routine for Women Over 40: Energy in 30 Min",
  "meta_description": "Discover the 6-step morning routine for women over 40 that boosts energy, sharpens focus, and brings calm every day. Science-backed habits that actually stick.",
  "product_handle": "brain-tonic",
  "cluster": "Brain",
  "word_count": 2050,
  "author": "Happy Aging Team"
}
